slcp/__init__.py
slcp/__main__.py
slcp/cli.py
slcp/log.py
slcp/process.py
slcp-0.3.0.dist-info/entry_points.txt
slcp-0.3.0.dist-info/LICENSE
slcp-0.3.0.dist-info/WHEEL
slcp-0.3.0.dist-info/METADATA
slcp-0.3.0.dist-info/RECORD
