Metadata-Version: 2.1
Name: slcp
Version: 0.3.0
Summary: Copy all files with given extensions from a directory and its subfolders to another directory.
Home-page: https://github.com/pltnk/selective_copy
License: MIT
Keywords: cli,copy,selective copy,slcp
Author: Kirill Plotnikov
Author-email: init@pltnk.dev
Requires-Python: >=3.7,<4.0
Classifier: License :: OSI Approved :: MIT License
Classifier: Programming Language :: Python :: 3
Classifier: Programming Language :: Python :: 3.7
Project-URL: Repository, https://github.com/pltnk/selective_copy
